yadisk_async/__init__.py
yadisk_async/common.py
yadisk_async/compat.py
yadisk_async/exceptions.py
yadisk_async/py.typed
yadisk_async/session.py
yadisk_async/settings.py
yadisk_async/utils.py
yadisk_async/yadisk.py
yadisk_async/api/__init__.py
yadisk_async/api/api_request.py
yadisk_async/api/auth.py
yadisk_async/api/disk.py
yadisk_async/api/operations.py
yadisk_async/api/resources.py
yadisk_async/objects/__init__.py
yadisk_async/objects/auth.py
yadisk_async/objects/disk.py
yadisk_async/objects/error_object.py
yadisk_async/objects/operations.py
yadisk_async/objects/resources.py
yadisk_async/objects/yadisk_object.py
yadisk_async-1.4.5.dist-info/COPYING
yadisk_async-1.4.5.dist-info/COPYING.lesser
yadisk_async-1.4.5.dist-info/METADATA
yadisk_async-1.4.5.dist-info/WHEEL
yadisk_async-1.4.5.dist-info/top_level.txt
yadisk_async-1.4.5.dist-info/RECORD
