Metadata-Version: 2.1
Name: yadisk-async
Version: 1.4.5
Summary: Библиотека-клиент REST API Яндекс.Диска с поддержкой async/await / Yandex.Disk REST API client library with async/await support
Home-page: https://github.com/ivknv/yadisk-async
Author: Ivan Konovalov
Author-email: ivknv0@gmail.com
License: LGPLv3
Project-URL: Source code, https://github.com/ivknv/yadisk-async
Project-URL: Documentation (EN), https://yadisk-async.readthedocs.io/en/latest
Project-URL: Documentation (RU), https://yadisk-async.readthedocs.io/ru/latest
Project-URL: Bug tracker, https://github.com/ivknv/yadisk-async/issues
Keywords: yandex yandex.disk rest async
Classifier: Development Status :: 7 - Inactive
Classifier: Intended Audience :: Developers
Classifier: License :: OSI Approved :: GNU Lesser General Public License v3 (LGPLv3)
Classifier: License :: OSI Approved :: GNU Lesser General Public License v3 or later (LGPLv3+)
Classifier: Programming Language :: Python
Classifier: Programming Language :: Python :: 3
Classifier: Operating System :: OS Independent
Classifier: Topic :: Internet
Classifier: Topic :: Software Development :: Libraries
Classifier: Topic :: Software Development :: Libraries :: Python Modules
Requires-Python: >=3.8
License-File: COPYING
License-File: COPYING.lesser
Requires-Dist: aiohttp
Requires-Dist: aiofiles
